faag_cli/__init__.py
faag_cli/constants/__init__.py
faag_cli/constants/app_enums.py
faag_cli/constants/constants.py
faag_cli/constants/formatter_config.py
faag_cli/constants/pylint_rules.py
faag_cli/constants/ruff_rules.py
faag_cli/core/__init__.py
faag_cli/core/app_generator.py
faag_cli/core/feature_generator.py
faag_cli/faag.py
faag_cli/templates/.env.jinja
faag_cli/templates/.flaskenv.jinja
faag_cli/templates/.gitignore.jinja
faag_cli/templates/base/__init__.jinja
faag_cli/templates/base/fast__init__.jinja
faag_cli/templates/base/flask__init__.jinja
faag_cli/templates/config/config.jinja
faag_cli/templates/config/config__init__.jinja
faag_cli/templates/config/constants.jinja
faag_cli/templates/connection/connection__init__.jinja
faag_cli/templates/controller/controller__init__.jinja
faag_cli/templates/controller/fast_controller.jinja
faag_cli/templates/controller/fast_controller__init__.jinja
faag_cli/templates/controller/flask_controller.jinja
faag_cli/templates/controller/flask_controller__init__.jinja
faag_cli/templates/controller/sample_controller.jinja
faag_cli/templates/dao/dao__init__.jinja
faag_cli/templates/dao/sample_dao.jinja
faag_cli/templates/model/model__init__.jinja
faag_cli/templates/model/sample_model.jinja
faag_cli/templates/schemas/response/common_response_schema.jinja
faag_cli/templates/schemas/response/user_response_schema.jinja
faag_cli/templates/schemas/schemas__init__.jinja
faag_cli/templates/service/sample_service.jinja
faag_cli/templates/service/service__init__.jinja
faag_cli/templates/utils/logger.jinja
faag_cli/templates/utils/utils__init__.jinja
faag_cli/utils/__init__.py
faag_cli/utils/faag_utils.py
faag_cli/utils/poetry_template_generator.py
faag_cli/utils/templates_loader.py
faag_cli-0.2.1.dist-info/LICENSE
faag_cli-0.2.1.dist-info/METADATA
faag_cli-0.2.1.dist-info/WHEEL
faag_cli-0.2.1.dist-info/entry_points.txt
faag_cli-0.2.1.dist-info/RECORD
