Metadata-Version: 2.1
Name: faag-cli
Version: 0.2.1
Summary: Flask/FastAPI Architecture Application Generator
Home-page: https://github.com/DevzoneCommunity/faag_cli
License: MIT
Keywords: FastAPI,Flask,SQLAlchemy,Poetry,Python,CLI,API,Application,Generator,Architecture,Faag
Author: Vetrichelvan
Author-email: pythonhubdev@gmail.com
Requires-Python: >=3.9,<4.0
Classifier: License :: OSI Approved :: MIT License
Classifier: Operating System :: OS Independent
Classifier: Programming Language :: Python :: 3
Classifier: Programming Language :: Python :: 3.9
Classifier: Programming Language :: Python :: 3.10
Classifier: Programming Language :: Python :: 3.11
Classifier: Programming Language :: Python :: 3
Classifier: Programming Language :: Python :: 3.10
Requires-Dist: Jinja2 (>=3.1.2,<4.0.0)
Requires-Dist: python-box (>=7.0.1,<8.0.0)
Requires-Dist: python-semantic-release (>=7.33.2,<8.0.0)
Requires-Dist: tomli-w (>=1.0.0,<2.0.0)
Requires-Dist: typer[all] (>=0.6.1,<0.8.0)
Project-URL: Repository, https://github.com/DevzoneCommunity/faag_cli
